aiotdlib/__init__.py
aiotdlib/client.py
aiotdlib/client_cache.py
aiotdlib/client_settings.py
aiotdlib/constants.py
aiotdlib/filters.py
aiotdlib/handlers.py
aiotdlib/middlewares.py
aiotdlib/py.typed
aiotdlib/tdjson.py
aiotdlib/utils.py
aiotdlib/api/__init__.py
aiotdlib/api/api.py
aiotdlib/api/errors/__init__.py
aiotdlib/api/errors/error.py
aiotdlib/api/functions/__init__.py
aiotdlib/api/functions/accept_call.py
aiotdlib/api/functions/accept_terms_of_service.py
aiotdlib/api/functions/activate_story_stealth_mode.py
aiotdlib/api/functions/add_bot_media_preview.py
aiotdlib/api/functions/add_chat_folder_by_invite_link.py
aiotdlib/api/functions/add_chat_member.py
aiotdlib/api/functions/add_chat_members.py
aiotdlib/api/functions/add_chat_to_list.py
aiotdlib/api/functions/add_contact.py
aiotdlib/api/functions/add_custom_server_language_pack.py
aiotdlib/api/functions/add_favorite_sticker.py
aiotdlib/api/functions/add_file_to_downloads.py
aiotdlib/api/functions/add_local_message.py
aiotdlib/api/functions/add_log_message.py
aiotdlib/api/functions/add_message_reaction.py
aiotdlib/api/functions/add_network_statistics.py
aiotdlib/api/functions/add_pending_paid_message_reaction.py
aiotdlib/api/functions/add_proxy.py
aiotdlib/api/functions/add_quick_reply_shortcut_inline_query_result_message.py
aiotdlib/api/functions/add_quick_reply_shortcut_message.py
aiotdlib/api/functions/add_quick_reply_shortcut_message_album.py
aiotdlib/api/functions/add_recent_sticker.py
aiotdlib/api/functions/add_recently_found_chat.py
aiotdlib/api/functions/add_saved_animation.py
aiotdlib/api/functions/add_saved_notification_sound.py
aiotdlib/api/functions/add_sticker_to_set.py
aiotdlib/api/functions/allow_bot_to_send_messages.py
aiotdlib/api/functions/allow_unpaid_messages_from_user.py
aiotdlib/api/functions/answer_callback_query.py
aiotdlib/api/functions/answer_custom_query.py
aiotdlib/api/functions/answer_inline_query.py
aiotdlib/api/functions/answer_pre_checkout_query.py
aiotdlib-0.27.6.dist-info/METADATA
aiotdlib-0.27.6.dist-info/WHEEL
aiotdlib-0.27.6.dist-info/entry_points.txt
aiotdlib-0.27.6.dist-info/licenses/LICENSE
aiotdlib-0.27.6.dist-info/RECORD
