Metadata-Version: 2.4
Name: aiotdlib
Version: 0.27.6
Summary: Python asyncio Telegram client based on TDLib
Project-URL: Source, https://github.com/pylakey/aiotdlib
Project-URL: Homepage, https://github.com/pylakey/aiotdlib
Author-email: pylakey <pylakey@protonmail.com>
Maintainer-email: pylakey <pylakey@protonmail.com>
License: MIT License
License-File: LICENSE
Classifier: Framework :: AsyncIO
Classifier: License :: OSI Approved :: MIT License
Classifier: Operating System :: MacOS
Classifier: Operating System :: POSIX :: BSD :: FreeBSD
Classifier: Operating System :: POSIX :: Linux
Classifier: Topic :: Software Development :: Libraries :: Python Modules
Classifier: Typing :: Typed
Requires-Python: >=3.9
Requires-Dist: pydantic-settings<3,>=2.1.0
Requires-Dist: pydantic<3,>=2
Requires-Dist: sortedcontainers>=2.4.0
Requires-Dist: ujson>=5
Provides-Extra: dev
Requires-Dist: black<25.0,>=23.3; extra == 'dev'
Requires-Dist: jinja2>=3.1.3; extra == 'dev'
Requires-Dist: pydash>=7.0.4; extra == 'dev'
